{
    "zeroinitiatives": "0innovations@sword-group.com",

    "oneinitiative": "1innovation@sword-group.com",

    "twoinitiatives": "2innovations@sword-group.com",

    "threeinitiatives": "3innovations@sword-group.com",

    "username0": "autouaser0@sword-group.com",

    "username1": "autouaser1@sword-group.com",

    "username2": "autouaser2@sword-group.com",

    "username3": "autouaser3@sword-group.com",

    "wrongusername": "adc@apple.gr",

    "wrongformatusername": "adc@def@gh",

    "validusername": "konstantinos.zagklis@sword-group.com",

    "globalportfolio": "portfolio@sword-group.com",

    "noportfolio": "noportfolio@sword-group.com",

    "climatemanager": "climatechangemanager@sword-group.com",

    "gendermanager": "genderequality@sword-group.com",

    "humanitarianmanager": "humanitarian@sword-group.com",

    "immunizationmanager": "immunization@sword-group.com",

    "learningmanager": "learning@sword-group.com",

    "healthmanager": "mchildhealth@sword-group.com",

    "mentalmanager": "mhapwellbeing@sword-group.com",

    "washmanager": "wash@sword-group.com",

    "youthmanager": "youth@sword-group.com",

    "adminuser": "admin@sword-group.com",
    
    "phaseuser": "phasetester@sword-group.com"
}